spotify_mcp/__init__.py
spotify_mcp/server.py
spotify_mcp/spotify_api.py
spotify_mcp/utils.py
spotify_mcp-0.1.0.dist-info/METADATA
spotify_mcp-0.1.0.dist-info/WHEEL
spotify_mcp-0.1.0.dist-info/entry_points.txt
spotify_mcp-0.1.0.dist-info/RECORD
