Metadata-Version: 2.4
Name: spotify-mcp
Version: 0.1.0
Summary: MCP spotify project
Author-email: Varun Srivastava <varun.neal@berkeley.edu>
Requires-Python: >=3.12
Requires-Dist: mcp>=1.0.0
Requires-Dist: python-dotenv>=1.0.1
Requires-Dist: spotipy==2.24.0
